{
    "memo": "25cefc344fde99ac53e2433e0bb622ab3c40f1a5c2ec8f8354e1d7e2a73b569d",
    "projects": [
        {
            "name": "github.com/labstack/echo",
            "branch": "master",
            "revision": "8fec907eec712eca150d79082c3a8ed63d402928",
            "packages": [
                "."
            ]
        },
        {
            "name": "github.com/labstack/gommon",
            "branch": "master",
            "revision": "f72d3c883f8ea180da8f085dd320804c41332ad1",
            "packages": [
                "color",
                "log"
            ]
        },
        {
            "name": "github.com/mattn/go-colorable",
            "branch": "master",
            "revision": "d228849504861217f796da67fae4f6e347643f15",
            "packages": [
                "."
            ]
        },
        {
            "name": "github.com/mattn/go-isatty",
            "branch": "master",
            "revision": "30a891c33c7cde7b02a981314b4228ec99380cca",
            "packages": [
                "."
            ]
        },
        {
            "name": "github.com/pkg/errors",
            "branch": "master",
            "revision": "248dadf4e9068a0b3e79f02ed0a610d935de5302",
            "packages": [
                "."
            ]
        },
        {
            "name": "github.com/satori/go.uuid",
            "branch": "master",
            "revision": "b061729afc07e77a8aa4fad0a2fd840958f1942a",
            "packages": [
                "."
            ]
        },
        {
            "name": "github.com/uber-go/atomic",
            "branch": "master",
            "revision": "3b8db5e93c4c02efbc313e17b2e796b0914a01fb",
            "packages": [
                "."
            ]
        },
        {
            "name": "github.com/uber-go/zap",
            "branch": "master",
            "revision": "a5783ee4b216a927da8f839c45cfbf9d694e1467",
            "packages": [
                "."
            ]
        },
        {
            "name": "github.com/valyala/bytebufferpool",
            "branch": "master",
            "revision": "e746df99fe4a3986f4d4f79e13c1e0117ce9c2f7",
            "packages": [
                "."
            ]
        },
        {
            "name": "github.com/valyala/fasttemplate",
            "branch": "master",
            "revision": "d090d65668a286d9a180d43a19dfdc5dcad8fe88",
            "packages": [
                "."
            ]
        },
        {
            "name": "golang.org/x/crypto",
            "branch": "master",
            "revision": "41d678d1df78cd0410143162dff954e6dc09300f",
            "packages": [
                "acme/autocert"
            ]
        },
        {
            "name": "golang.org/x/net",
            "branch": "master",
            "revision": "f2499483f923065a842d38eb4c7f1927e6fc6e6d",
            "packages": [
                "context",
                "context/ctxhttp"
            ]
        },
        {
            "name": "golang.org/x/sys",
            "branch": "master",
            "revision": "d75a52659825e75fff6158388dddc6a5b04f9ba5",
            "packages": [
                "unix"
            ]
        },
        {
            "name": "gopkg.in/redis.v5",
            "branch": "master",
            "revision": "8829ddcd8bdb333e477cc845946c4b9b2ef66280",
            "packages": [
                "."
            ]
        }
    ]
}
